tests/__init__.py
trapeze/__init__.py
trapeze/__main__.py
trapeze/app.py
trapeze/modules/__init__.py
trapeze/modules/trapeze.py
trapeze-0.0.25.dist-info/LICENSE
trapeze-0.0.25.dist-info/METADATA
trapeze-0.0.25.dist-info/WHEEL
trapeze-0.0.25.dist-info/entry_points.txt
trapeze-0.0.25.dist-info/top_level.txt
trapeze-0.0.25.dist-info/RECORD
