Metadata-Version: 2.1
Name: trapeze
Version: 0.0.25
Summary: Store/restore configuration and credentials for applications with AWS S3
Home-page: https://bitbucket.org/ericgee/trapeze
Author: Eric Gee
Author-email: eric@gee.farm
License: UNKNOWN
Platform: UNKNOWN
Classifier: Programming Language :: Python :: 3.6
Classifier: License :: OSI Approved :: MIT License
Classifier: Operating System :: OS Independent
Requires-Dist: boto3
Requires-Dist: click
Requires-Dist: colorama
